README.rst
setup.cfg
setup.py
PsiberLogic/FuzzySetup.py
PsiberLogic/LICENSE.txt
PsiberLogic/README.txt
PsiberLogic/__init__.py
PsiberLogic/cPsiberLogic.pyx
PsiberLogic/utilities.py
PsiberLogic.egg-info/PKG-INFO
PsiberLogic.egg-info/SOURCES.txt
PsiberLogic.egg-info/dependency_links.txt
PsiberLogic.egg-info/requires.txt
PsiberLogic.egg-info/top_level.txt
PsiberLogic/demo/TipFIS.py
PsiberLogic/demo/__init__.py