Metadata-Version: 1.1
Name: PsiberLogic
Version: 3.0.1
Summary: A speed-optimized, barebones, Python 3 fuzzy controller package.
Home-page: http://packages.python.org/psiberlogic
Author: Psibernetix Inc.
Author-email: contact@psibernetix.com
License: GNU Library or Lesser General Public License (LGPL)
Keywords: Fuzzy Logic
Platform: UNKNOWN
Classifier: Development Status :: 5 - Production/Stable
Classifier: License :: OSI Approved :: GNU Library or Lesser General Public License (LGPL)
Classifier: Programming Language :: Python :: 3
Classifier: Intended Audience :: Developers
Classifier: Intended Audience :: Education
Classifier: Intended Audience :: Science/Research
Classifier: Topic :: Scientific/Engineering
